lighteval/__init__.py
lighteval/__main__.py
lighteval/cli_args.py
lighteval/data.py
lighteval/main_accelerate.py
lighteval/main_baseline.py
lighteval/main_custom.py
lighteval/main_endpoint.py
lighteval/main_inspect.py
lighteval/main_nanotron.py
lighteval/main_sglang.py
lighteval/main_tasks.py
lighteval/main_vllm.py
lighteval/pipeline.py
lighteval/logging/evaluation_tracker.py
lighteval/logging/info_loggers.py
lighteval/metrics/__init__.py
lighteval/metrics/dynamic_metrics.py
lighteval/metrics/metrics.py
lighteval/metrics/metrics_corpus.py
lighteval/metrics/metrics_sample.py
lighteval/metrics/normalizations.py
lighteval/metrics/sample_preparator.py
lighteval/metrics/harness_compatibility/drop.py
lighteval/metrics/harness_compatibility/truthful_qa.py
lighteval/metrics/imports/__init__.py
lighteval/metrics/imports/bert_scorer.py
lighteval/metrics/imports/data_stats_metric.py
lighteval/metrics/imports/data_stats_utils.py
lighteval/metrics/imports/summac.py
lighteval/metrics/utils/extractive_match_utils.py
lighteval/metrics/utils/judge_utils.py
lighteval/metrics/utils/linguistic_tokenizers.py
lighteval/metrics/utils/llm_as_judge.py
lighteval/metrics/utils/math_comparison.py
lighteval/metrics/utils/metric_utils.py
lighteval/metrics/utils/stderr.py
lighteval/models/abstract_model.py
lighteval/models/model_input.py
lighteval/models/model_loader.py
lighteval/models/model_output.py
lighteval/models/utils.py
lighteval/models/custom/custom_model.py
lighteval/models/dummy/dummy_model.py
lighteval/models/endpoints/endpoint_model.py
lighteval/models/endpoints/inference_providers_model.py
lighteval/models/endpoints/litellm_model.py
lighteval/models/endpoints/tgi_model.py
lighteval/models/nanotron/nanotron_model.py
lighteval/models/sglang/sglang_model.py
lighteval/models/transformers/adapter_model.py
lighteval/models/transformers/delta_model.py
lighteval/models/transformers/transformers_model.py
lighteval/models/transformers/vlm_transformers_model.py
lighteval-0.12.2.dist-info/licenses/LICENSE
lighteval-0.12.2.dist-info/METADATA
lighteval-0.12.2.dist-info/WHEEL
lighteval-0.12.2.dist-info/entry_points.txt
lighteval-0.12.2.dist-info/top_level.txt
lighteval-0.12.2.dist-info/RECORD
