Metadata-Version: 2.4
Name: lighteval
Version: 0.12.2
Summary: A lightweight and configurable evaluation package
Author-email: Nathan Habib <nathan.habib@huggingface.com>, Clémentine Fourrier <clementine@huggingface.com>, Thomas Wolf <thom@huggingface.com>
Maintainer-email: Nathan Habib <nathan.habib@huggingface.com>, Clémentine Fourrier <clementine@huggingface.com>
License: MIT License
Project-URL: Homepage, https://github.com/huggingface/lighteval
Project-URL: Issues, https://github.com/huggingface/lighteval/issues
Keywords: evaluation,nlp,llm
Classifier: Development Status :: 3 - Alpha
Classifier: Intended Audience :: Developers
Classifier: Programming Language :: Python :: 3.10
Classifier: License :: OSI Approved :: MIT License
Classifier: Operating System :: OS Independent
Requires-Python: >=3.10
License-File: LICENSE
Requires-Dist: transformers>=4.54.0
Requires-Dist: inspect-ai>=0.3.140
Requires-Dist: openai
Requires-Dist: accelerate
Requires-Dist: huggingface_hub[hf_xet]>=0.30.2
Requires-Dist: torch<3.0,>=2.0
Requires-Dist: GitPython>=3.1.41
Requires-Dist: datasets>=4.0.0
Requires-Dist: pydantic
Requires-Dist: numpy>=2
Requires-Dist: hf-xet>=1.1.8
Requires-Dist: typer>=0.20.0
Requires-Dist: termcolor==2.3.0
Requires-Dist: pytablewriter
Requires-Dist: rich
Requires-Dist: colorlog
Requires-Dist: aenum==3.1.15
Requires-Dist: nltk==3.9.1
Requires-Dist: scikit-learn
Requires-Dist: sacrebleu
Requires-Dist: rouge_score==0.1.2
Requires-Dist: sentencepiece>=0.1.99
Requires-Dist: protobuf
Requires-Dist: pycountry
Requires-Dist: fsspec>=2023.12.2
Requires-Dist: httpx>=0.27.2
Requires-Dist: latex2sympy2_extended==1.0.6
Requires-Dist: langcodes
Provides-Extra: litellm
Requires-Dist: litellm[caching]>=1.66.0; extra == "litellm"
Requires-Dist: diskcache; extra == "litellm"
Provides-Extra: tgi
Requires-Dist: text-generation>=0.7.0; extra == "tgi"
Provides-Extra: optimum
Requires-Dist: optimum==1.12.0; extra == "optimum"
Provides-Extra: quantization
Requires-Dist: bitsandbytes>=0.41.0; extra == "quantization"
Requires-Dist: auto-gptq>=0.4.2; extra == "quantization"
Provides-Extra: adapters
Requires-Dist: peft==0.3.0; extra == "adapters"
Provides-Extra: nanotron
Requires-Dist: nanotron; extra == "nanotron"
Requires-Dist: tensorboardX; extra == "nanotron"
Provides-Extra: tensorboardx
Requires-Dist: tensorboardX; extra == "tensorboardx"
Provides-Extra: vllm
Requires-Dist: vllm<0.10.2,>=0.10.0; extra == "vllm"
Requires-Dist: ray; extra == "vllm"
Requires-Dist: more_itertools; extra == "vllm"
Provides-Extra: sglang
Requires-Dist: sglang; extra == "sglang"
Provides-Extra: quality
Requires-Dist: ruff>=v0.11.0; extra == "quality"
Requires-Dist: pre-commit; extra == "quality"
Provides-Extra: tests
Requires-Dist: pytest>=7.4.0; extra == "tests"
Requires-Dist: deepdiff; extra == "tests"
Requires-Dist: pip>=25.2; extra == "tests"
Provides-Extra: dev
Requires-Dist: lighteval[accelerate,extended_tasks,math,multilingual,quality,tests,vllm]; extra == "dev"
Provides-Extra: docs
Requires-Dist: hf-doc-builder; extra == "docs"
Requires-Dist: watchdog; extra == "docs"
Provides-Extra: extended-tasks
Requires-Dist: langdetect; extra == "extended-tasks"
Requires-Dist: openai>1.87; extra == "extended-tasks"
Requires-Dist: tiktoken; extra == "extended-tasks"
Requires-Dist: emoji; extra == "extended-tasks"
Requires-Dist: spacy; extra == "extended-tasks"
Requires-Dist: syllapy; extra == "extended-tasks"
Requires-Dist: evaluate; extra == "extended-tasks"
Provides-Extra: s3
Requires-Dist: s3fs; extra == "s3"
Provides-Extra: multilingual
Requires-Dist: stanza; extra == "multilingual"
Requires-Dist: spacy[ja,ko,th]>=3.8.0; extra == "multilingual"
Requires-Dist: jieba; extra == "multilingual"
Requires-Dist: pyvi; extra == "multilingual"
Provides-Extra: math
Requires-Dist: latex2sympy2_extended==1.0.6; extra == "math"
Provides-Extra: wandb
Requires-Dist: wandb; extra == "wandb"
Provides-Extra: trackio
Requires-Dist: trackio; extra == "trackio"
Dynamic: license-file
